fsm_utils-0.1.1.dist-info/METADATA
fsm_utils-0.1.1.dist-info/WHEEL
function_sampler/logger.py
function_sampler/__init__.py
function_sampler/regex_constants.py
function_sampler/config/__init__.py
function_sampler/config/config.py
function_sampler/config/utils.py
function_sampler/config/token_mapper.py
function_sampler/json.py
function_sampler/fsm/__init__.py
function_sampler/fsm/fsm.py
function_sampler/fsm/tokenizer_fsm_patch.py
function_sampler/fsm/utils.py
function_sampler/fsm/fsm_utils/src/tokenizer_index.rs
function_sampler/fsm/fsm_utils/src/lib.rs
function_sampler/fsm/regex.py
function_sampler/sampler.py
function_sampler/utils.py
function_sampler/cache.py
function_sampler/fsm/fsm_utils.cpython-310-x86_64-linux-gnu.so
fsm_utils-0.1.1.dist-info/RECORD
