Metadata-Version: 2.3
Name: fsm_utils
Version: 0.1.1
